dipolar/__init__.py
dipolar/cli.py
dipolar/dipole.py
dipolar/layer.py
dipolar/network.py
dipolar/neuron.py
dipolar/metrics/__init__.py
dipolar/metrics/evaluation.py
dipolar/utils/__init__.py
dipolar/utils/geometry.py
dipolar/utils/validation.py
dipolar_network-0.2.2.dist-info/licenses/LICENCE
dipolar_network-0.2.2.dist-info/METADATA
dipolar_network-0.2.2.dist-info/WHEEL
dipolar_network-0.2.2.dist-info/entry_points.txt
dipolar_network-0.2.2.dist-info/top_level.txt
dipolar_network-0.2.2.dist-info/RECORD
