Metadata-Version: 2.4
Name: dipolar-network
Version: 0.2.2
Summary: A library for constructing dipolar separating hyperplanes
Author-email: Michal Dziekonski <mimi020001@gmail.com>
Project-URL: Homepage, https://github.com/mimiaczekpluszaczek/dipolar_network
Classifier: Programming Language :: Python :: 3
Classifier: License :: OSI Approved :: MIT License
Classifier: Operating System :: OS Independent
Requires-Python: >=3.7
License-File: LICENCE
Requires-Dist: numpy
Requires-Dist: scikit-learn
Dynamic: license-file
